debug_util/__init__.py
debug_util/core.py
duyan_debug-0.0.6.dist-info/LICENSE
duyan_debug-0.0.6.dist-info/METADATA
duyan_debug-0.0.6.dist-info/WHEEL
duyan_debug-0.0.6.dist-info/top_level.txt
duyan_debug-0.0.6.dist-info/RECORD
