Metadata-Version: 2.1
Name: duyan-debug
Version: 0.0.6
Summary: Using for Debug, finding problem
Home-page: https://github.com/pypa/sampleproject
Author: WuMenghao
Author-email: menghao.wu@duyansoft.com
License: UNKNOWN
Project-URL: Bug Tracker, https://github.com/pypa/sampleproject/issues
Platform: UNKNOWN
Classifier: Programming Language :: Python :: 3
Classifier: License :: OSI Approved :: MIT License
Classifier: Operating System :: OS Independent
Requires-Python: >=3.6
License-File: LICENSE
Requires-Dist: objgraph
Requires-Dist: guppy3
